hooklib.py
hooklib_git.py
hooklib_hg.py
hooklib_input.py
setup.py
hooklib.egg-info/PKG-INFO
hooklib.egg-info/SOURCES.txt
hooklib.egg-info/dependency_links.txt
hooklib.egg-info/pbr.json
hooklib.egg-info/top_level.txt