Metadata-Version: 1.0
Name: hooklib
Version: 0.2.1
Summary: Hook helper library in python
Home-page: UNKNOWN
Author: Laurent Charignon
Author-email: l.charignon@gmail.com
License: UNKNOWN
Keywords: hooks
Platform: UNKNOWN
